pyevalai/__init__.py
pyevalai/pyevalai.py
pyevalai/pyevalai_server.py
pyevalai/utils.py
pyevalai/server/__init__.py
pyevalai/server/ai.py
pyevalai/server/ai_grader.py
pyevalai/server/database.py
pyevalai/server/ldap.py
pyevalai/server/login.py
pyevalai/server/website.py
pyevalai/server/websocket_server.py
pyevalai-0.0.7.dist-info/METADATA
pyevalai-0.0.7.dist-info/WHEEL
pyevalai-0.0.7.dist-info/top_level.txt
pyevalai-0.0.7.dist-info/RECORD
