Metadata-Version: 2.1
Name: pyevalai
Version: 0.0.7
Summary: Automated python exercise evaluations with AI.
Author: Nils Wandel
Author-email: <wandeln@cs.uni-bonn.de>
Project-URL: Source Code, https://github.com/wandeln/pyevalai
Keywords: jupyter,exercise,evaluation,AI,LLM
Classifier: Development Status :: 3 - Alpha
Classifier: Intended Audience :: Developers
Classifier: Programming Language :: Python :: 3
Classifier: Operating System :: Unix
Classifier: Operating System :: MacOS :: MacOS X
Classifier: Operating System :: Microsoft :: Windows
Requires-Python: >=3.8
Requires-Dist: numpy
Requires-Dist: tornado
Requires-Dist: cloudpickle
Requires-Dist: ipywidgets
Requires-Dist: natsort
Requires-Dist: jinja2
Requires-Dist: markdown2>=2.4.0
